event_processing/__init__.py
event_processing/engine.py
event_processing/event.py
event_processing/subscriber.py
event_processing-0.0.12.dist-info/LICENSE
event_processing-0.0.12.dist-info/METADATA
event_processing-0.0.12.dist-info/WHEEL
event_processing-0.0.12.dist-info/top_level.txt
event_processing-0.0.12.dist-info/RECORD
