Metadata-Version: 2.1
Name: event-processing
Version: 0.0.12
Summary: Simple Event Processing Library
Home-page: https://github.com/raulikeda/EventProcessing
Author: Raul Ikeda
License: MIT
Project-URL: Bug Tracker, https://github.com/raulikeda/EventProcessing/issues
Classifier: Programming Language :: Python :: 3
Classifier: License :: OSI Approved :: MIT License
Classifier: Operating System :: OS Independent
Requires-Python: >=3.6
License-File: LICENSE
